[
    {
        "version": "dubbo-3.0.3",
        "release_date": "18-Sep-2021",
        "criticality_score": "Not Available",
        "scorecard": "4.2",
        "cve_details": [
            {
                "Year": "2020",
                "of_Vulnerabilities": 2,
                "DoS": null,
                "Code Execution": 1,
                "Overflow": null,
                "Memory_Corruption": null,
                "Sql_Injection": null,
                "XSS": null,
                "Directory_Traversal": null,
                "Http_Response_Splitting": null,
                "Bypass_something": null,
                "Gain_Information": null,
                "Gain_Privileges": null,
                "CSRF": null,
                "File_Inclusion": null,
                "of_exploits": ""
            },
            {
                "Year": "2021",
                "of_Vulnerabilities": 10,
                "DoS": null,
                "Code Execution": 1,
                "Overflow": null,
                "Memory_Corruption": null,
                "Sql_Injection": null,
                "XSS": null,
                "Directory_Traversal": null,
                "Http_Response_Splitting": null,
                "Bypass_something": 1,
                "Gain_Information": null,
                "Gain_Privileges": null,
                "CSRF": null,
                "File_Inclusion": null,
                "of_exploits": ""
            },
            {
                "Year": "2022",
                "of_Vulnerabilities": 3,
                "DoS": null,
                "Code_Execution": 2,
                "Overflow": null,
                "Memory_Corruption": null,
                "Sql_Injection": null,
                "XSS": null,
                "Directory_Traversal": null,
                "Http_Response_Splitting": null,
                "Bypass_something": 1,
                "Gain_Information": null,
                "Gain_Privileges": null,
                "CSRF": null,
                "File_Inclusion": null,
                "of_exploits": ""
            },
            {
                "Year": "2023",
                "of_Vulnerabilities": 2,
                "DoS": null,
                "Code_Execution": 2,
                "Overflow": null,
                "Memory_Corruption": null,
                "Sql_Injection": null,
                "XSS": null,
                "Directory_Traversal": null,
                "Http_Response_Splitting": null,
                "Bypass_something": null,
                "Gain_Information": null,
                "Gain_Privileges": null,
                "CSRF": null,
                "File_Inclusion": null,
                "of_exploits": ""
            },
            {
                "Year": "Total",
                "# of Vulnerabilities": 17,
                "DoS": null,
                "Code_Execution": 6,
                "Overflow": null,
                "Memory_Corruption": null,
                "Sql_Injection": null,
                "XSS": null,
                "Directory_Traversal": null,
                "Http_Response_Splitting": null,
                "Bypass_something": 2,
                "Gain_Information": null,
                "Gain_Privileges": null,
                "CSRF": null,
                "File_Inclusion": null,
                "of_exploits": ""
            }
        ]
    },
    {
        "version": "dubbo-3.1.0",
        "release_date": "17-Aug-2022",
        "criticality_score": "0.45116",
        "scorecard": "3.5",
        "cve_details": "Not Available"
    },
    {
        "version": "dubbo-3.2.4",
        "release_date": "30-Jun-2023",
        "criticality_score": 0.47754,
        "scorecard": 6.4,
        "cve_details": "Not Available"
    }
]